{
  "MD033": {
    "allowed_elements": [
      "h1",
      "h2",
      "h3",
      "h4",
      "span",
      "br",
      "a",
      "p",
      "figure",
      "figcaption",
      "map",
      "area",
      "body",
      "hr",
      "dl",
      "dt",
      "dd",
      "ul",
      "ol",
      "li",
      "pre",
      "iframe",
      "form",
      "label",
      "input",
      "fieldset",
      "legend",
      "datalist",
      "option",
      "table",
      "caption",
      "thead",
      "tbody",
      "tfoot",
      "meta",
      "style",
      "link",
      "tr",
      "th",
      "td"
    ]
  },
  "MD013": {
    "heading_line_length": 256,
    "code_block_line_length": 256,
    "line_length": 256
  },
  "MD024": {
    "allow_different_nesting": true
  }
}